imagestogif_js/__init__.py
imagestogif_js/converter.py
imagestogif_js-1.0.0.dist-info/LICENSE
imagestogif_js-1.0.0.dist-info/METADATA
imagestogif_js-1.0.0.dist-info/WHEEL
imagestogif_js-1.0.0.dist-info/top_level.txt
imagestogif_js-1.0.0.dist-info/RECORD
